excel_scraper/__init__.py
excel_scraper/excel_scraper.py
test/__init__.py
test/test_excel_scraper.py
excel_scraper-0.0.7.dist-info/METADATA
excel_scraper-0.0.7.dist-info/WHEEL
excel_scraper-0.0.7.dist-info/top_level.txt
excel_scraper-0.0.7.dist-info/RECORD
